pipelinesds/__init__.py
pipelinesds/pipeliner.py
pipelinesds/tester.py
pipelinesds-1.0.4.dist-info/METADATA
pipelinesds-1.0.4.dist-info/WHEEL
pipelinesds-1.0.4.dist-info/top_level.txt
pipelinesds-1.0.4.dist-info/RECORD
