Metadata-Version: 2.1
Name: pipelinesds
Version: 1.0.4
Summary: Solution for DS Team
Author: DS Team
Author-email: ds@sts.pl
Classifier: Programming Language :: Python :: 3
Classifier: License :: OSI Approved :: MIT License
Classifier: Operating System :: OS Independent
Requires-Python: >=3.11
Requires-Dist: google-cloud-bigquery
Requires-Dist: google-cloud-bigquery-storage
Requires-Dist: google-cloud-storage
Requires-Dist: pandas
Requires-Dist: db-dtypes
Requires-Dist: evidently
